{
  "name": "Chinese Moving Washes",
  "universe": "Private Universe",
  "fixtures": [
    {
      "channel": 301,
      "type": "Chinese Moving Wash",
      "group": "rearSides",
      "options": []
    },
    {
      "channel": 315,
      "type": "Chinese Moving Wash",
      "group": "rearSides",
      "options": []
    },
    {
      "channel": 329,
      "type": "Chinese Moving Wash",
      "group": "rearSides",
      "options": []
    },
    {
      "channel": 343,
      "type": "Chinese Moving Wash",
      "group": "rearSides",
      "options": []
    }
  ]
}
